Metadata-Version: 2.1
Name: dash-chartjs
Version: 0.0.7
Summary: A Dash Component library for ChartJs.
Home-page: https://github.com/zenalytiks/dash-chartjs.git
Author: Waleed Malik <waleed@zenalytiks.com>
License: MIT
Classifier: Framework :: Dash
License-File: LICENSE
